{"name":"Calorieburner","tagline":"Feel the difference","body":"***\r\n### Bienvenue sur la page du projet CalorieBurner\r\nCette application _android_ a été réalisé dans le cadre d'un projet informatique de 3ème année d'école d'ingénieurs qui s'est déroulée en 2 parties:\r\n<br>\r\n1. Une implémentation UML (_Unified Modeling Language_) de l'ensemble de l'application\r\n<br> 2. Un développement sur plateforme android 4.2.2\r\n\r\n## Qu'est ce que l'on peut faire avec ?\r\nTout le monde n'est pas sportif mais tout le monde mange, avec _CalorieBurner_ vous allez pouvoir faire les actions suivantes:\r\n* Composer vos repas.\r\n* Éliminer les calories consommées en faisant un sport ou une activité physique.\r\n* Faire du sport.\r\n* Partager vos résultats sur les réseaux sociaux\r\n<br> _Attention elle ne se substitue pas un diététicien_\r\n\r\n### Si je suis perdu ?\r\n* Une aide est disponible sur toutes les fenêtres de l'application\r\n\r\n##Le code source :\r\nCelui-ci est divisé en packages afin de faciliter une relecture de plus le code comporte certaines annotations.\r\n <br> pour permettre une importation sur téléphone, compilez-le en utilisant _eclipse_(nombreux tutoriels sur internet), veillez à bien disposer des derniers _google SDK_.\r\n\r\n##En cas de problèmes ou questions ?\r\nVous pouvez envoyer un mail a : teamcalorieburner[at]gmail.com\r\n\r\n","google":"","note":"Don't delete this file! It's used internally to help with page regeneration."}